alchemlyb/__init__.py
alchemlyb/_version.py
alchemlyb/convergence/__init__.py
alchemlyb/convergence/convergence.py
alchemlyb/convergence/pade.py
alchemlyb/estimators/__init__.py
alchemlyb/estimators/bar_.py
alchemlyb/estimators/base.py
alchemlyb/estimators/mbar_.py
alchemlyb/estimators/ti_.py
alchemlyb/estimators/ti_gaussian_quadrature_.py
alchemlyb/parsing/__init__.py
alchemlyb/parsing/amber.py
alchemlyb/parsing/gmx.py
alchemlyb/parsing/gomc.py
alchemlyb/parsing/namd.py
alchemlyb/parsing/parquet.py
alchemlyb/parsing/util.py
alchemlyb/postprocessors/__init__.py
alchemlyb/postprocessors/units.py
alchemlyb/preprocessing/__init__.py
alchemlyb/preprocessing/subsampling.py
alchemlyb/tests/__init__.py
alchemlyb/tests/conftest.py
alchemlyb/tests/test_convergence.py
alchemlyb/tests/test_fep_estimators.py
alchemlyb/tests/test_import.py
alchemlyb/tests/test_preprocessing.py
alchemlyb/tests/test_ti_estimators.py
alchemlyb/tests/test_ti_gaussian_quadrature.py
alchemlyb/tests/test_units.py
alchemlyb/tests/test_version.py
alchemlyb/tests/test_visualisation.py
alchemlyb/tests/test_workflow.py
alchemlyb/tests/test_workflow_ABFE.py
alchemlyb/tests/parsing/__init__.py
alchemlyb/tests/parsing/test_amber.py
alchemlyb/tests/parsing/test_gmx.py
alchemlyb/tests/parsing/test_gomc.py
alchemlyb/tests/parsing/test_namd.py
alchemlyb/tests/parsing/test_parquet.py
alchemlyb/tests/parsing/test_util.py
alchemlyb/visualisation/__init__.py
alchemlyb/visualisation/convergence.py
alchemlyb/visualisation/dF_state.py
alchemlyb/visualisation/mbar_matrix.py
alchemlyb/visualisation/ti_dhdl.py
alchemlyb/workflows/__init__.py
alchemlyb/workflows/abfe.py
alchemlyb/workflows/base.py
alchemlyb-2.5.0.dist-info/licenses/AUTHORS
alchemlyb-2.5.0.dist-info/licenses/LICENSE
alchemlyb-2.5.0.dist-info/METADATA
alchemlyb-2.5.0.dist-info/WHEEL
alchemlyb-2.5.0.dist-info/top_level.txt
alchemlyb-2.5.0.dist-info/RECORD
