Metadata-Version: 2.4
Name: alchemlyb
Version: 2.5.0
Summary: the simple alchemistry library
Author-email: Zhiyi Wu <william@zhiyiwu.me>, David Dotson <dotsdl@gmail.com>
Maintainer-email: Zhiyi Wu <william@zhiyiwu.me>, Oliver Beckstein <orbeckst@gmail.com>
License-Expression: BSD-3-Clause
Project-URL: Homepage, https://github.com/alchemistry/alchemlyb
Project-URL: Documentation, https://alchemlyb.readthedocs.io/
Project-URL: Repository, https://github.com/alchemistry/alchemlyb
Project-URL: Issues, https://github.com/alchemistry/alchemlyb/issues
Project-URL: Changelog, https://github.com/alchemistry/alchemlyb/blob/master/CHANGES
Project-URL: Discussions, https://github.com/alchemistry/alchemlyb/discussions
Keywords: free energy,MBAR,thermodynamic integration,free energy perturbation,FEP,alchemistry,analysis,GROMACS,NAMD,AMBER,molecular dynamics
Classifier: Development Status :: 5 - Production/Stable
Classifier: Intended Audience :: Science/Research
Classifier: Operating System :: POSIX
Classifier: Operating System :: MacOS :: MacOS X
Classifier: Operating System :: Microsoft :: Windows
Classifier: Programming Language :: Python
Classifier: Programming Language :: Python :: 3
Classifier: Programming Language :: Python :: 3.11
Classifier: Programming Language :: Python :: 3.12
Classifier: Programming Language :: Python :: 3.13
Classifier: Programming Language :: Python :: 3.14
Classifier: Topic :: Scientific/Engineering
Classifier: Topic :: Scientific/Engineering :: Bio-Informatics
Classifier: Topic :: Scientific/Engineering :: Chemistry
Classifier: Topic :: Software Development :: Libraries :: Python Modules
Requires-Python: >=3.11
License-File: LICENSE
License-File: AUTHORS
Requires-Dist: numpy!=2.3.0,!=2.3.1,!=2.3.2
Requires-Dist: pandas>=2.1
Requires-Dist: pymbar>=4
Requires-Dist: scipy
Requires-Dist: scikit-learn
Requires-Dist: matplotlib>=3.7
Requires-Dist: loguru
Requires-Dist: pyarrow
Requires-Dist: joblib
Provides-Extra: tests
Requires-Dist: pytest; extra == "tests"
Requires-Dist: alchemtest; extra == "tests"
Dynamic: license-file
